eth_trader_api/__init__.py
eth_trader_api/proto.py
eth_trader_api_proto-0.0.8.dist-info/METADATA
eth_trader_api_proto-0.0.8.dist-info/WHEEL
eth_trader_api_proto-0.0.8.dist-info/top_level.txt
eth_trader_api_proto-0.0.8.dist-info/RECORD
