Metadata-Version: 2.1
Name: eth-trader-api-proto
Version: 0.0.8
Summary: proto-generated files for eth-trader-api
Requires-Dist: betterproto (==v2.0.0b5)
